COPYING.md
MANIFEST.in
README.md
setup.py
djungle/__init__.py
djungle/modernizer/__init__.py
djungle/modernizer/static/djungle/modernizer/html5shiv-printshiv.js
djungle/modernizer/static/djungle/modernizer/html5shiv.js
djungle/modernizer/templates/djungle/modernizer/chrome-frame.html
djungle/modernizer/templates/djungle/modernizer/html.html
djungle/modernizer/templates/djungle/modernizer/html5shiv.html
djungle_modernizer.egg-info/PKG-INFO
djungle_modernizer.egg-info/SOURCES.txt
djungle_modernizer.egg-info/dependency_links.txt
djungle_modernizer.egg-info/namespace_packages.txt
djungle_modernizer.egg-info/not-zip-safe
djungle_modernizer.egg-info/requires.txt
djungle_modernizer.egg-info/top_level.txt